azuresshconfig.py
azuresshconfig-0.3.0.dist-info/DESCRIPTION.rst
azuresshconfig-0.3.0.dist-info/METADATA
azuresshconfig-0.3.0.dist-info/RECORD
azuresshconfig-0.3.0.dist-info/WHEEL
azuresshconfig-0.3.0.dist-info/entry_points.txt
azuresshconfig-0.3.0.dist-info/metadata.json
azuresshconfig-0.3.0.dist-info/top_level.txt
