Metadata-Version: 2.0
Name: azuresshconfig
Version: 0.3.0
Summary: Generate SSH config file from Azure ARM VM inventry in subscription
Home-page: https://github.com/yokawasa/azure-ssh-config
Author: Yoichi Kawasaki
Author-email: yoichi.kawasaki@outlook.com
License: MIT
Keywords: azure ssh config
Platform: any
Classifier: Environment :: Console
Classifier: Intended Audience :: Developers
Classifier: Intended Audience :: System Administrators
Classifier: License :: OSI Approved :: MIT License
Classifier: Programming Language :: Python :: 2.7
Classifier: Programming Language :: Python :: 3
Classifier: Programming Language :: Python :: 3.3
Classifier: Programming Language :: Python :: 3.4
Classifier: Programming Language :: Python :: 3.5
Classifier: Programming Language :: Python :: 3.6
Classifier: Topic :: Utilities
Requires-Dist: argparse
Requires-Dist: azure-mgmt-compute (>=0.30.0rc6)
Requires-Dist: azure-mgmt-network (>=0.30.0rc6)
Requires-Dist: azure-mgmt-resource (>=0.30.0rc6)
Requires-Dist: msrestazure
Requires-Dist: simplejson
